extend_me.py
extend_me-1.1.5.dist-info/LICENSE
extend_me-1.1.5.dist-info/METADATA
extend_me-1.1.5.dist-info/WHEEL
extend_me-1.1.5.dist-info/top_level.txt
extend_me-1.1.5.dist-info/RECORD
