Metadata-Version: 2.1
Name: extend_me
Version: 1.1.5
Summary: Class based extension/plugin library
Home-page: https://github.com/katyukha/extend-me
Author: Dmytro Katyukha
Author-email: dmytro.katyukha@gmail.com
License: MPL 2.0
Keywords: extension,plugin
Classifier: Development Status :: 5 - Production/Stable
Classifier: Intended Audience :: Developers
Classifier: License :: OSI Approved :: Mozilla Public License 2.0 (MPL 2.0)
Classifier: Programming Language :: Python
Classifier: Programming Language :: Python :: 2
Classifier: Programming Language :: Python :: 3
Classifier: Topic :: Software Development :: Libraries
Classifier: Topic :: Software Development :: Libraries :: Python Modules
License-File: LICENSE
